[
    {
        "af": 6,
        "avg": 182.4993433333,
        "dst_addr": "2001:500:200::b",
        "dst_name": "2001:500:200::b",
        "dup": 0,
        "from": "2001:470:1f15:525:a62b:b0ff:fee0:7b0",
        "fw": 4970,
        "lts": 57,
        "max": 182.578815,
        "min": 182.36347,
        "msm_id": 2010,
        "msm_name": "Ping",
        "prb_id": 30677,
        "proto": "ICMP",
        "rcvd": 3,
        "result": [
            {
                "rtt": 182.36347
            },
            {
                "rtt": 182.578815
            },
            {
                "rtt": 182.555745
            }
        ],
        "sent": 3,
        "size": 20,
        "src_addr": "2001:470:1f15:525:a62b:b0ff:fee0:7b0",
        "step": 240,
        "stored_timestamp": 1559829242,
        "timestamp": 1559829135,
        "ttl": 50,
        "type": "ping"
    },
    {
        "af": 6,
        "avg": 182.65757,
        "dst_addr": "2001:500:200::b",
        "dst_name": "2001:500:200::b",
        "dup": 0,
        "from": "2001:470:1f15:525:a62b:b0ff:fee0:7b0",
        "fw": 4970,
        "lts": 5,
        "max": 182.766075,
        "min": 182.565265,
        "msm_id": 2010,
        "msm_name": "Ping",
        "prb_id": 30677,
        "proto": "ICMP",
        "rcvd": 3,
        "result": [
            {
                "rtt": 182.64137
            },
            {
                "rtt": 182.565265
            },
            {
                "rtt": 182.766075
            }
        ],
        "sent": 3,
        "size": 20,
        "src_addr": "2001:470:1f15:525:a62b:b0ff:fee0:7b0",
        "step": 240,
        "stored_timestamp": 1559829532,
        "timestamp": 1559829376,
        "ttl": 50,
        "type": "ping"
    },
    {
        "af": 6,
        "avg": 182.3173483333,
        "dst_addr": "2001:500:200::b",
        "dst_name": "2001:500:200::b",
        "dup": 0,
        "from": "2001:470:1f15:525:a62b:b0ff:fee0:7b0",
        "fw": 4970,
        "lts": 28,
        "max": 182.616145,
        "min": 181.889875,
        "msm_id": 2010,
        "msm_name": "Ping",
        "prb_id": 30677,
        "proto": "ICMP",
        "rcvd": 3,
        "result": [
            {
                "rtt": 181.889875
            },
            {
                "rtt": 182.616145
            },
            {
                "rtt": 182.446025
            }
        ],
        "sent": 3,
        "size": 20,
        "src_addr": "2001:470:1f15:525:a62b:b0ff:fee0:7b0",
        "step": 240,
        "stored_timestamp": 1559829681,
        "timestamp": 1559829617,
        "ttl": 50,
        "type": "ping"
    },
    {
        "af": 6,
        "avg": 183.882495,
        "dst_addr": "2001:500:200::b",
        "dst_name": "2001:500:200::b",
        "dup": 0,
        "from": "2001:470:1f15:525:a62b:b0ff:fee0:7b0",
        "fw": 4970,
        "lts": 42,
        "max": 186.611125,
        "min": 182.347275,
        "msm_id": 2010,
        "msm_name": "Ping",
        "prb_id": 30677,
        "proto": "ICMP",
        "rcvd": 3,
        "result": [
            {
                "rtt": 186.611125
            },
            {
                "rtt": 182.347275
            },
            {
                "rtt": 182.689085
            }
        ],
        "sent": 3,
        "size": 20,
        "src_addr": "2001:470:1f15:525:a62b:b0ff:fee0:7b0",
        "step": 240,
        "stored_timestamp": 1559829956,
        "timestamp": 1559829855,
        "ttl": 50,
        "type": "ping"
    },
    {
        "af": 6,
        "avg": 182.1521316667,
        "dst_addr": "2001:500:200::b",
        "dst_name": "2001:500:200::b",
        "dup": 0,
        "from": "2001:470:1f15:525:a62b:b0ff:fee0:7b0",
        "fw": 4970,
        "lts": 3,
        "max": 182.56808,
        "min": 181.75646,
        "msm_id": 2010,
        "msm_name": "Ping",
        "prb_id": 30677,
        "proto": "ICMP",
        "rcvd": 3,
        "result": [
            {
                "rtt": 182.56808
            },
            {
                "rtt": 181.75646
            },
            {
                "rtt": 182.131855
            }
        ],
        "sent": 3,
        "size": 20,
        "src_addr": "2001:470:1f15:525:a62b:b0ff:fee0:7b0",
        "step": 240,
        "stored_timestamp": 1559830775,
        "timestamp": 1559830094,
        "ttl": 50,
        "type": "ping"
    },
    {
        "af": 6,
        "avg": 182.5115333333,
        "dst_addr": "2001:500:200::b",
        "dst_name": "2001:500:200::b",
        "dup": 0,
        "from": "2001:470:1f15:525:a62b:b0ff:fee0:7b0",
        "fw": 4970,
        "lts": 22,
        "max": 182.62964,
        "min": 182.35894,
        "msm_id": 2010,
        "msm_name": "Ping",
        "prb_id": 30677,
        "proto": "ICMP",
        "rcvd": 3,
        "result": [
            {
                "rtt": 182.62964
            },
            {
                "rtt": 182.54602
            },
            {
                "rtt": 182.35894
            }
        ],
        "sent": 3,
        "size": 20,
        "src_addr": "2001:470:1f15:525:a62b:b0ff:fee0:7b0",
        "step": 240,
        "stored_timestamp": 1559831096,
        "timestamp": 1559830335,
        "ttl": 50,
        "type": "ping"
    },
    {
        "af": 6,
        "avg": 182.4888133333,
        "dst_addr": "2001:500:200::b",
        "dst_name": "2001:500:200::b",
        "dup": 0,
        "from": "2001:470:1f15:525:a62b:b0ff:fee0:7b0",
        "fw": 4970,
        "lts": 45,
        "max": 182.61237,
        "min": 182.415385,
        "msm_id": 2010,
        "msm_name": "Ping",
        "prb_id": 30677,
        "proto": "ICMP",
        "rcvd": 3,
        "result": [
            {
                "rtt": 182.61237
            },
            {
                "rtt": 182.438685
            },
            {
                "rtt": 182.415385
            }
        ],
        "sent": 3,
        "size": 20,
        "src_addr": "2001:470:1f15:525:a62b:b0ff:fee0:7b0",
        "step": 240,
        "stored_timestamp": 1559831226,
        "timestamp": 1559830574,
        "ttl": 50,
        "type": "ping"
    },
    {
        "af": 6,
        "avg": 182.5875566667,
        "dst_addr": "2001:500:200::b",
        "dst_name": "2001:500:200::b",
        "dup": 0,
        "from": "2001:470:1f15:525:a62b:b0ff:fee0:7b0",
        "fw": 4970,
        "lts": 20,
        "max": 182.888375,
        "min": 182.401975,
        "msm_id": 2010,
        "msm_name": "Ping",
        "prb_id": 30677,
        "proto": "ICMP",
        "rcvd": 3,
        "result": [
            {
                "rtt": 182.401975
            },
            {
                "rtt": 182.47232
            },
            {
                "rtt": 182.888375
            }
        ],
        "sent": 3,
        "size": 20,
        "src_addr": "2001:470:1f15:525:a62b:b0ff:fee0:7b0",
        "step": 240,
        "stored_timestamp": 1559831451,
        "timestamp": 1559830816,
        "ttl": 50,
        "type": "ping"
    },
    {
        "af": 6,
        "avg": 182.6086883333,
        "dst_addr": "2001:500:200::b",
        "dst_name": "2001:500:200::b",
        "dup": 0,
        "from": "2001:470:1f15:525:a62b:b0ff:fee0:7b0",
        "fw": 4970,
        "lts": 23,
        "max": 182.866985,
        "min": 182.19489,
        "msm_id": 2010,
        "msm_name": "Ping",
        "prb_id": 30677,
        "proto": "ICMP",
        "rcvd": 3,
        "result": [
            {
                "rtt": 182.866985
            },
            {
                "rtt": 182.76419
            },
            {
                "rtt": 182.19489
            }
        ],
        "sent": 3,
        "size": 20,
        "src_addr": "2001:470:1f15:525:a62b:b0ff:fee0:7b0",
        "step": 240,
        "stored_timestamp": 1559831688,
        "timestamp": 1559831056,
        "ttl": 50,
        "type": "ping"
    },
    {
        "af": 6,
        "avg": 182.5572633333,
        "dst_addr": "2001:500:200::b",
        "dst_name": "2001:500:200::b",
        "dup": 0,
        "from": "2001:470:1f15:525:a62b:b0ff:fee0:7b0",
        "fw": 4970,
        "lts": 59,
        "max": 182.73673,
        "min": 182.45532,
        "msm_id": 2010,
        "msm_name": "Ping",
        "prb_id": 30677,
        "proto": "ICMP",
        "rcvd": 3,
        "result": [
            {
                "rtt": 182.45532
            },
            {
                "rtt": 182.73673
            },
            {
                "rtt": 182.47974
            }
        ],
        "sent": 3,
        "size": 20,
        "src_addr": "2001:470:1f15:525:a62b:b0ff:fee0:7b0",
        "step": 240,
        "stored_timestamp": 1559831815,
        "timestamp": 1559831294,
        "ttl": 50,
        "type": "ping"
    },
    {
        "af": 6,
        "avg": 182.4091033333,
        "dst_addr": "2001:500:200::b",
        "dst_name": "2001:500:200::b",
        "dup": 0,
        "from": "2001:470:1f15:525:a62b:b0ff:fee0:7b0",
        "fw": 4970,
        "lts": 57,
        "max": 182.969285,
        "min": 181.81545,
        "msm_id": 2010,
        "msm_name": "Ping",
        "prb_id": 30677,
        "proto": "ICMP",
        "rcvd": 3,
        "result": [
            {
                "rtt": 182.969285
            },
            {
                "rtt": 182.442575
            },
            {
                "rtt": 181.81545
            }
        ],
        "sent": 3,
        "size": 20,
        "src_addr": "2001:470:1f15:525:a62b:b0ff:fee0:7b0",
        "step": 240,
        "stored_timestamp": 1559831929,
        "timestamp": 1559831537,
        "ttl": 50,
        "type": "ping"
    },
    {
        "af": 6,
        "avg": 188.021915,
        "dst_addr": "2001:500:200::b",
        "dst_name": "2001:500:200::b",
        "dup": 0,
        "from": "2001:470:1f15:525:a62b:b0ff:fee0:7b0",
        "fw": 4970,
        "lts": 21,
        "max": 191.34359,
        "min": 182.598775,
        "msm_id": 2010,
        "msm_name": "Ping",
        "prb_id": 30677,
        "proto": "ICMP",
        "rcvd": 3,
        "result": [
            {
                "rtt": 182.598775
            },
            {
                "rtt": 191.34359
            },
            {
                "rtt": 190.12338
            }
        ],
        "sent": 3,
        "size": 20,
        "src_addr": "2001:470:1f15:525:a62b:b0ff:fee0:7b0",
        "step": 240,
        "stored_timestamp": 1559832045,
        "timestamp": 1559831774,
        "ttl": 50,
        "type": "ping"
    },
    {
        "af": 6,
        "avg": 182.312415,
        "dst_addr": "2001:500:200::b",
        "dst_name": "2001:500:200::b",
        "dup": 0,
        "from": "2001:470:1f15:525:a62b:b0ff:fee0:7b0",
        "fw": 4970,
        "lts": 42,
        "max": 182.783795,
        "min": 181.81888,
        "msm_id": 2010,
        "msm_name": "Ping",
        "prb_id": 30677,
        "proto": "ICMP",
        "rcvd": 3,
        "result": [
            {
                "rtt": 182.783795
            },
            {
                "rtt": 182.33457
            },
            {
                "rtt": 181.81888
            }
        ],
        "sent": 3,
        "size": 20,
        "src_addr": "2001:470:1f15:525:a62b:b0ff:fee0:7b0",
        "step": 240,
        "stored_timestamp": 1559832169,
        "timestamp": 1559832014,
        "ttl": 50,
        "type": "ping"
    },
    {
        "af": 6,
        "avg": 182.7131816667,
        "dst_addr": "2001:500:200::b",
        "dst_name": "2001:500:200::b",
        "dup": 0,
        "from": "2001:470:1f15:525:a62b:b0ff:fee0:7b0",
        "fw": 4970,
        "lts": 10,
        "max": 182.81229,
        "min": 182.63739,
        "msm_id": 2010,
        "msm_name": "Ping",
        "prb_id": 30677,
        "proto": "ICMP",
        "rcvd": 3,
        "result": [
            {
                "rtt": 182.81229
            },
            {
                "rtt": 182.63739
            },
            {
                "rtt": 182.689865
            }
        ],
        "sent": 3,
        "size": 20,
        "src_addr": "2001:470:1f15:525:a62b:b0ff:fee0:7b0",
        "step": 240,
        "stored_timestamp": 1559832396,
        "timestamp": 1559832255,
        "ttl": 50,
        "type": "ping"
    },
    {
        "af": 6,
        "avg": 182.67028,
        "dst_addr": "2001:500:200::b",
        "dst_name": "2001:500:200::b",
        "dup": 0,
        "from": "2001:470:1f15:525:a62b:b0ff:fee0:7b0",
        "fw": 4970,
        "lts": 24,
        "max": 182.75314,
        "min": 182.57732,
        "msm_id": 2010,
        "msm_name": "Ping",
        "prb_id": 30677,
        "proto": "ICMP",
        "rcvd": 3,
        "result": [
            {
                "rtt": 182.75314
            },
            {
                "rtt": 182.68038
            },
            {
                "rtt": 182.57732
            }
        ],
        "sent": 3,
        "size": 20,
        "src_addr": "2001:470:1f15:525:a62b:b0ff:fee0:7b0",
        "step": 240,
        "stored_timestamp": 1559832611,
        "timestamp": 1559832496,
        "ttl": 50,
        "type": "ping"
    }
]