[
    {
        "af": 6,
        "avg": 117.9054083333,
        "dst_addr": "2001:500:2f::f",
        "dst_name": "2001:500:2f::f",
        "dup": 0,
        "from": "2001:1670:8:edda:ea94:f6ff:fee3:7354",
        "fw": 4970,
        "lts": 31,
        "max": 117.94733,
        "min": 117.838415,
        "msm_id": 2004,
        "msm_name": "Ping",
        "prb_id": 20922,
        "proto": "ICMP",
        "rcvd": 3,
        "result": [
            {
                "rtt": 117.93048
            },
            {
                "rtt": 117.94733
            },
            {
                "rtt": 117.838415
            }
        ],
        "sent": 3,
        "size": 20,
        "src_addr": "2001:1670:8:edda:ea94:f6ff:fee3:7354",
        "step": 240,
        "stored_timestamp": 1556697734,
        "timestamp": 1556697673,
        "ttl": 56,
        "type": "ping"
    },
    {
        "af": 6,
        "avg": 117.930355,
        "dst_addr": "2001:500:2f::f",
        "dst_name": "2001:500:2f::f",
        "dup": 0,
        "from": "2001:1670:8:edda:ea94:f6ff:fee3:7354",
        "fw": 4970,
        "lts": 13,
        "max": 117.952935,
        "min": 117.91773,
        "msm_id": 2004,
        "msm_name": "Ping",
        "prb_id": 20922,
        "proto": "ICMP",
        "rcvd": 3,
        "result": [
            {
                "rtt": 117.952935
            },
            {
                "rtt": 117.91773
            },
            {
                "rtt": 117.9204
            }
        ],
        "sent": 3,
        "size": 20,
        "src_addr": "2001:1670:8:edda:ea94:f6ff:fee3:7354",
        "step": 240,
        "stored_timestamp": 1556698002,
        "timestamp": 1556697916,
        "ttl": 56,
        "type": "ping"
    },
    {
        "af": 6,
        "avg": 117.8651416667,
        "dst_addr": "2001:500:2f::f",
        "dst_name": "2001:500:2f::f",
        "dup": 0,
        "from": "2001:1670:8:edda:ea94:f6ff:fee3:7354",
        "fw": 4970,
        "lts": 2,
        "max": 117.97795,
        "min": 117.692105,
        "msm_id": 2004,
        "msm_name": "Ping",
        "prb_id": 20922,
        "proto": "ICMP",
        "rcvd": 3,
        "result": [
            {
                "rtt": 117.92537
            },
            {
                "rtt": 117.97795
            },
            {
                "rtt": 117.692105
            }
        ],
        "sent": 3,
        "size": 20,
        "src_addr": "2001:1670:8:edda:ea94:f6ff:fee3:7354",
        "step": 240,
        "stored_timestamp": 1556698292,
        "timestamp": 1556698155,
        "ttl": 56,
        "type": "ping"
    },
    {
        "af": 6,
        "avg": 117.9502733333,
        "dst_addr": "2001:500:2f::f",
        "dst_name": "2001:500:2f::f",
        "dup": 0,
        "from": "2001:1670:8:edda:ea94:f6ff:fee3:7354",
        "fw": 4970,
        "lts": 24,
        "max": 118.02589,
        "min": 117.91211,
        "msm_id": 2004,
        "msm_name": "Ping",
        "prb_id": 20922,
        "proto": "ICMP",
        "rcvd": 3,
        "result": [
            {
                "rtt": 118.02589
            },
            {
                "rtt": 117.91211
            },
            {
                "rtt": 117.91282
            }
        ],
        "sent": 3,
        "size": 20,
        "src_addr": "2001:1670:8:edda:ea94:f6ff:fee3:7354",
        "step": 240,
        "stored_timestamp": 1556698454,
        "timestamp": 1556698394,
        "ttl": 56,
        "type": "ping"
    },
    {
        "af": 6,
        "avg": 133.5354833333,
        "dst_addr": "2001:500:2f::f",
        "dst_name": "2001:500:2f::f",
        "dup": 0,
        "from": "2001:1670:8:edda:ea94:f6ff:fee3:7354",
        "fw": 4970,
        "lts": 1,
        "max": 138.589525,
        "min": 125.50216,
        "msm_id": 2004,
        "msm_name": "Ping",
        "prb_id": 20922,
        "proto": "ICMP",
        "rcvd": 3,
        "result": [
            {
                "rtt": 136.514765
            },
            {
                "rtt": 138.589525
            },
            {
                "rtt": 125.50216
            }
        ],
        "sent": 3,
        "size": 20,
        "src_addr": "2001:1670:8:edda:ea94:f6ff:fee3:7354",
        "step": 240,
        "stored_timestamp": 1556698745,
        "timestamp": 1556698635,
        "ttl": 54,
        "type": "ping"
    },
    {
        "af": 6,
        "avg": 117.8881633333,
        "dst_addr": "2001:500:2f::f",
        "dst_name": "2001:500:2f::f",
        "dup": 0,
        "from": "2001:1670:8:edda:ea94:f6ff:fee3:7354",
        "fw": 4970,
        "lts": 68,
        "max": 117.939905,
        "min": 117.824095,
        "msm_id": 2004,
        "msm_name": "Ping",
        "prb_id": 20922,
        "proto": "ICMP",
        "rcvd": 3,
        "result": [
            {
                "rtt": 117.939905
            },
            {
                "rtt": 117.824095
            },
            {
                "rtt": 117.90049
            }
        ],
        "sent": 3,
        "size": 20,
        "src_addr": "2001:1670:8:edda:ea94:f6ff:fee3:7354",
        "step": 240,
        "stored_timestamp": 1556699008,
        "timestamp": 1556698873,
        "ttl": 56,
        "type": "ping"
    },
    {
        "af": 6,
        "avg": 117.7160983333,
        "dst_addr": "2001:500:2f::f",
        "dst_name": "2001:500:2f::f",
        "dup": 0,
        "from": "2001:1670:8:edda:ea94:f6ff:fee3:7354",
        "fw": 4970,
        "lts": 24,
        "max": 117.961325,
        "min": 117.31862,
        "msm_id": 2004,
        "msm_name": "Ping",
        "prb_id": 20922,
        "proto": "ICMP",
        "rcvd": 3,
        "result": [
            {
                "rtt": 117.961325
            },
            {
                "rtt": 117.86835
            },
            {
                "rtt": 117.31862
            }
        ],
        "sent": 3,
        "size": 20,
        "src_addr": "2001:1670:8:edda:ea94:f6ff:fee3:7354",
        "step": 240,
        "stored_timestamp": 1556699183,
        "timestamp": 1556699114,
        "ttl": 56,
        "type": "ping"
    },
    {
        "af": 6,
        "avg": 117.8437133333,
        "dst_addr": "2001:500:2f::f",
        "dst_name": "2001:500:2f::f",
        "dup": 0,
        "from": "2001:1670:8:edda:ea94:f6ff:fee3:7354",
        "fw": 4970,
        "lts": 1,
        "max": 117.885445,
        "min": 117.79608,
        "msm_id": 2004,
        "msm_name": "Ping",
        "prb_id": 20922,
        "proto": "ICMP",
        "rcvd": 3,
        "result": [
            {
                "rtt": 117.885445
            },
            {
                "rtt": 117.849615
            },
            {
                "rtt": 117.79608
            }
        ],
        "sent": 3,
        "size": 20,
        "src_addr": "2001:1670:8:edda:ea94:f6ff:fee3:7354",
        "step": 240,
        "stored_timestamp": 1556699452,
        "timestamp": 1556699356,
        "ttl": 56,
        "type": "ping"
    },
    {
        "af": 6,
        "avg": 117.8448733333,
        "dst_addr": "2001:500:2f::f",
        "dst_name": "2001:500:2f::f",
        "dup": 0,
        "from": "2001:1670:8:edda:ea94:f6ff:fee3:7354",
        "fw": 4970,
        "lts": 2,
        "max": 117.87977,
        "min": 117.80381,
        "msm_id": 2004,
        "msm_name": "Ping",
        "prb_id": 20922,
        "proto": "ICMP",
        "rcvd": 3,
        "result": [
            {
                "rtt": 117.85104
            },
            {
                "rtt": 117.87977
            },
            {
                "rtt": 117.80381
            }
        ],
        "sent": 3,
        "size": 20,
        "src_addr": "2001:1670:8:edda:ea94:f6ff:fee3:7354",
        "step": 240,
        "stored_timestamp": 1556699734,
        "timestamp": 1556699595,
        "ttl": 56,
        "type": "ping"
    },
    {
        "af": 6,
        "avg": 117.9057283333,
        "dst_addr": "2001:500:2f::f",
        "dst_name": "2001:500:2f::f",
        "dup": 0,
        "from": "2001:1670:8:edda:ea94:f6ff:fee3:7354",
        "fw": 4970,
        "lts": 37,
        "max": 117.976285,
        "min": 117.86681,
        "msm_id": 2004,
        "msm_name": "Ping",
        "prb_id": 20922,
        "proto": "ICMP",
        "rcvd": 3,
        "result": [
            {
                "rtt": 117.976285
            },
            {
                "rtt": 117.87409
            },
            {
                "rtt": 117.86681
            }
        ],
        "sent": 3,
        "size": 20,
        "src_addr": "2001:1670:8:edda:ea94:f6ff:fee3:7354",
        "step": 240,
        "stored_timestamp": 1556699909,
        "timestamp": 1556699834,
        "ttl": 56,
        "type": "ping"
    },
    {
        "af": 6,
        "avg": 117.8900883333,
        "dst_addr": "2001:500:2f::f",
        "dst_name": "2001:500:2f::f",
        "dup": 0,
        "from": "2001:1670:8:edda:ea94:f6ff:fee3:7354",
        "fw": 4970,
        "lts": 11,
        "max": 117.935405,
        "min": 117.81441,
        "msm_id": 2004,
        "msm_name": "Ping",
        "prb_id": 20922,
        "proto": "ICMP",
        "rcvd": 3,
        "result": [
            {
                "rtt": 117.92045
            },
            {
                "rtt": 117.81441
            },
            {
                "rtt": 117.935405
            }
        ],
        "sent": 3,
        "size": 20,
        "src_addr": "2001:1670:8:edda:ea94:f6ff:fee3:7354",
        "step": 240,
        "stored_timestamp": 1556700275,
        "timestamp": 1556700074,
        "ttl": 56,
        "type": "ping"
    },
    {
        "af": 6,
        "avg": 117.9100733333,
        "dst_addr": "2001:500:2f::f",
        "dst_name": "2001:500:2f::f",
        "dup": 0,
        "from": "2001:1670:8:edda:ea94:f6ff:fee3:7354",
        "fw": 4970,
        "lts": 0,
        "max": 117.98076,
        "min": 117.79755,
        "msm_id": 2004,
        "msm_name": "Ping",
        "prb_id": 20922,
        "proto": "ICMP",
        "rcvd": 3,
        "result": [
            {
                "rtt": 117.95191
            },
            {
                "rtt": 117.79755
            },
            {
                "rtt": 117.98076
            }
        ],
        "sent": 3,
        "size": 20,
        "src_addr": "2001:1670:8:edda:ea94:f6ff:fee3:7354",
        "step": 240,
        "stored_timestamp": 1556700451,
        "timestamp": 1556700313,
        "ttl": 56,
        "type": "ping"
    },
    {
        "af": 6,
        "avg": 117.9030633333,
        "dst_addr": "2001:500:2f::f",
        "dst_name": "2001:500:2f::f",
        "dup": 0,
        "from": "2001:1670:8:edda:ea94:f6ff:fee3:7354",
        "fw": 4970,
        "lts": 31,
        "max": 118.05947,
        "min": 117.69124,
        "msm_id": 2004,
        "msm_name": "Ping",
        "prb_id": 20922,
        "proto": "ICMP",
        "rcvd": 3,
        "result": [
            {
                "rtt": 118.05947
            },
            {
                "rtt": 117.95848
            },
            {
                "rtt": 117.69124
            }
        ],
        "sent": 3,
        "size": 20,
        "src_addr": "2001:1670:8:edda:ea94:f6ff:fee3:7354",
        "step": 240,
        "stored_timestamp": 1556700646,
        "timestamp": 1556700554,
        "ttl": 56,
        "type": "ping"
    },
    {
        "af": 6,
        "avg": 117.81335,
        "dst_addr": "2001:500:2f::f",
        "dst_name": "2001:500:2f::f",
        "dup": 0,
        "from": "2001:1670:8:edda:ea94:f6ff:fee3:7354",
        "fw": 4970,
        "lts": 100,
        "max": 117.93449,
        "min": 117.74986,
        "msm_id": 2004,
        "msm_name": "Ping",
        "prb_id": 20922,
        "proto": "ICMP",
        "rcvd": 3,
        "result": [
            {
                "rtt": 117.93449
            },
            {
                "rtt": 117.7557
            },
            {
                "rtt": 117.74986
            }
        ],
        "sent": 3,
        "size": 20,
        "src_addr": "2001:1670:8:edda:ea94:f6ff:fee3:7354",
        "step": 240,
        "stored_timestamp": 1556700890,
        "timestamp": 1556700796,
        "ttl": 56,
        "type": "ping"
    },
    {
        "af": 6,
        "avg": 118.044215,
        "dst_addr": "2001:500:2f::f",
        "dst_name": "2001:500:2f::f",
        "dup": 0,
        "from": "2001:1670:8:edda:ea94:f6ff:fee3:7354",
        "fw": 4970,
        "lts": 53,
        "max": 118.10252,
        "min": 117.958475,
        "msm_id": 2004,
        "msm_name": "Ping",
        "prb_id": 20922,
        "proto": "ICMP",
        "rcvd": 3,
        "result": [
            {
                "rtt": 118.10252
            },
            {
                "rtt": 118.07165
            },
            {
                "rtt": 117.958475
            }
        ],
        "sent": 3,
        "size": 20,
        "src_addr": "2001:1670:8:edda:ea94:f6ff:fee3:7354",
        "step": 240,
        "stored_timestamp": 1556701160,
        "timestamp": 1556701035,
        "ttl": 56,
        "type": "ping"
    }
]