[
    {
        "af": 6,
        "avg": 138.1637716667,
        "dst_addr": "2001:500:9f::42",
        "dst_name": "2001:500:9f::42",
        "dup": 0,
        "from": "2a01:5ec0:2027:4494:c225:e9ff:fea8:7c54",
        "fw": 4780,
        "lts": 23,
        "max": 142.89744,
        "min": 134.783695,
        "msm_id": 2008,
        "msm_name": "Ping",
        "prb_id": 34057,
        "proto": "ICMP",
        "rcvd": 3,
        "result": [
            {
                "rtt": 142.89744
            },
            {
                "rtt": 136.81018
            },
            {
                "rtt": 134.783695
            }
        ],
        "sent": 3,
        "size": 20,
        "src_addr": "2a01:5ec0:2027:4494:c225:e9ff:fea8:7c54",
        "step": 240,
        "stored_timestamp": 1559829206,
        "timestamp": 1559829128,
        "ttl": 45,
        "type": "ping"
    },
    {
        "af": 6,
        "avg": 134.9587666667,
        "dst_addr": "2001:500:9f::42",
        "dst_name": "2001:500:9f::42",
        "dup": 0,
        "from": "2a01:5ec0:2027:4494:c225:e9ff:fea8:7c54",
        "fw": 4780,
        "lts": 83,
        "max": 136.80191,
        "min": 133.891895,
        "msm_id": 2008,
        "msm_name": "Ping",
        "prb_id": 34057,
        "proto": "ICMP",
        "rcvd": 3,
        "result": [
            {
                "rtt": 136.80191
            },
            {
                "rtt": 134.182495
            },
            {
                "rtt": 133.891895
            }
        ],
        "sent": 3,
        "size": 20,
        "src_addr": "2a01:5ec0:2027:4494:c225:e9ff:fea8:7c54",
        "step": 240,
        "stored_timestamp": 1559829473,
        "timestamp": 1559829368,
        "ttl": 45,
        "type": "ping"
    },
    {
        "af": 6,
        "avg": 129.2064016667,
        "dst_addr": "2001:500:9f::42",
        "dst_name": "2001:500:9f::42",
        "dup": 0,
        "from": "2a01:5ec0:2027:4494:c225:e9ff:fea8:7c54",
        "fw": 4780,
        "lts": 53,
        "max": 133.624675,
        "min": 126.567095,
        "msm_id": 2008,
        "msm_name": "Ping",
        "prb_id": 34057,
        "proto": "ICMP",
        "rcvd": 3,
        "result": [
            {
                "rtt": 133.624675
            },
            {
                "rtt": 127.427435
            },
            {
                "rtt": 126.567095
            }
        ],
        "sent": 3,
        "size": 20,
        "src_addr": "2a01:5ec0:2027:4494:c225:e9ff:fea8:7c54",
        "step": 240,
        "stored_timestamp": 1559829787,
        "timestamp": 1559829606,
        "ttl": 45,
        "type": "ping"
    },
    {
        "af": 6,
        "avg": 157.2387883333,
        "dst_addr": "2001:500:9f::42",
        "dst_name": "2001:500:9f::42",
        "dup": 0,
        "from": "2a01:5ec0:2027:4494:c225:e9ff:fea8:7c54",
        "fw": 4780,
        "lts": 20,
        "max": 161.61018,
        "min": 154.167325,
        "msm_id": 2008,
        "msm_name": "Ping",
        "prb_id": 34057,
        "proto": "ICMP",
        "rcvd": 3,
        "result": [
            {
                "rtt": 161.61018
            },
            {
                "rtt": 155.93886
            },
            {
                "rtt": 154.167325
            }
        ],
        "sent": 3,
        "size": 20,
        "src_addr": "2a01:5ec0:2027:4494:c225:e9ff:fea8:7c54",
        "step": 240,
        "stored_timestamp": 1559829922,
        "timestamp": 1559829847,
        "ttl": 45,
        "type": "ping"
    },
    {
        "af": 6,
        "avg": 124.6355766667,
        "dst_addr": "2001:500:9f::42",
        "dst_name": "2001:500:9f::42",
        "dup": 0,
        "from": "2a01:5ec0:2027:4494:c225:e9ff:fea8:7c54",
        "fw": 4780,
        "lts": 5,
        "max": 128.793025,
        "min": 122.18238,
        "msm_id": 2008,
        "msm_name": "Ping",
        "prb_id": 34057,
        "proto": "ICMP",
        "rcvd": 3,
        "result": [
            {
                "rtt": 128.793025
            },
            {
                "rtt": 122.931325
            },
            {
                "rtt": 122.18238
            }
        ],
        "sent": 3,
        "size": 20,
        "src_addr": "2a01:5ec0:2027:4494:c225:e9ff:fea8:7c54",
        "step": 240,
        "stored_timestamp": 1559830723,
        "timestamp": 1559830085,
        "ttl": 45,
        "type": "ping"
    },
    {
        "af": 6,
        "avg": 214.63978,
        "dst_addr": "2001:500:9f::42",
        "dst_name": "2001:500:9f::42",
        "dup": 0,
        "from": "2a01:5ec0:2027:4494:c225:e9ff:fea8:7c54",
        "fw": 4780,
        "lts": 65,
        "max": 217.768365,
        "min": 210.740375,
        "msm_id": 2008,
        "msm_name": "Ping",
        "prb_id": 34057,
        "proto": "ICMP",
        "rcvd": 3,
        "result": [
            {
                "rtt": 215.4106
            },
            {
                "rtt": 217.768365
            },
            {
                "rtt": 210.740375
            }
        ],
        "sent": 3,
        "size": 20,
        "src_addr": "2a01:5ec0:2027:4494:c225:e9ff:fea8:7c54",
        "step": 240,
        "stored_timestamp": 1559830939,
        "timestamp": 1559830327,
        "ttl": 45,
        "type": "ping"
    },
    {
        "af": 6,
        "avg": 151.6895216667,
        "dst_addr": "2001:500:9f::42",
        "dst_name": "2001:500:9f::42",
        "dup": 0,
        "from": "2a01:5ec0:2027:4494:c225:e9ff:fea8:7c54",
        "fw": 4780,
        "lts": 5,
        "max": 154.22307,
        "min": 149.643785,
        "msm_id": 2008,
        "msm_name": "Ping",
        "prb_id": 34057,
        "proto": "ICMP",
        "rcvd": 3,
        "result": [
            {
                "rtt": 151.20171
            },
            {
                "rtt": 149.643785
            },
            {
                "rtt": 154.22307
            }
        ],
        "sent": 3,
        "size": 20,
        "src_addr": "2a01:5ec0:2027:4494:c225:e9ff:fea8:7c54",
        "step": 240,
        "stored_timestamp": 1559831118,
        "timestamp": 1559830568,
        "ttl": 45,
        "type": "ping"
    },
    {
        "af": 6,
        "avg": 147.2931666667,
        "dst_addr": "2001:500:9f::42",
        "dst_name": "2001:500:9f::42",
        "dup": 0,
        "from": "2a01:5ec0:2027:4494:c225:e9ff:fea8:7c54",
        "fw": 4780,
        "lts": 4,
        "max": 160.01156,
        "min": 123.367875,
        "msm_id": 2008,
        "msm_name": "Ping",
        "prb_id": 34057,
        "proto": "ICMP",
        "rcvd": 3,
        "result": [
            {
                "rtt": 123.367875
            },
            {
                "rtt": 160.01156
            },
            {
                "rtt": 158.500065
            }
        ],
        "sent": 3,
        "size": 20,
        "src_addr": "2a01:5ec0:2027:4494:c225:e9ff:fea8:7c54",
        "step": 240,
        "stored_timestamp": 1559831288,
        "timestamp": 1559830806,
        "ttl": 45,
        "type": "ping"
    },
    {
        "af": 6,
        "avg": 145.2436116667,
        "dst_addr": "2001:500:9f::42",
        "dst_name": "2001:500:9f::42",
        "dup": 0,
        "from": "2a01:5ec0:2027:4494:c225:e9ff:fea8:7c54",
        "fw": 4780,
        "lts": 52,
        "max": 149.293375,
        "min": 142.43858,
        "msm_id": 2008,
        "msm_name": "Ping",
        "prb_id": 34057,
        "proto": "ICMP",
        "rcvd": 3,
        "result": [
            {
                "rtt": 149.293375
            },
            {
                "rtt": 143.99888
            },
            {
                "rtt": 142.43858
            }
        ],
        "sent": 3,
        "size": 20,
        "src_addr": "2a01:5ec0:2027:4494:c225:e9ff:fea8:7c54",
        "step": 240,
        "stored_timestamp": 1559831488,
        "timestamp": 1559831046,
        "ttl": 45,
        "type": "ping"
    },
    {
        "af": 6,
        "avg": 128.3447933333,
        "dst_addr": "2001:500:9f::42",
        "dst_name": "2001:500:9f::42",
        "dup": 0,
        "from": "2a01:5ec0:2027:4494:c225:e9ff:fea8:7c54",
        "fw": 4780,
        "lts": 31,
        "max": 132.42806,
        "min": 125.391465,
        "msm_id": 2008,
        "msm_name": "Ping",
        "prb_id": 34057,
        "proto": "ICMP",
        "rcvd": 3,
        "result": [
            {
                "rtt": 132.42806
            },
            {
                "rtt": 127.214855
            },
            {
                "rtt": 125.391465
            }
        ],
        "sent": 3,
        "size": 20,
        "src_addr": "2a01:5ec0:2027:4494:c225:e9ff:fea8:7c54",
        "step": 240,
        "stored_timestamp": 1559831616,
        "timestamp": 1559831286,
        "ttl": 45,
        "type": "ping"
    },
    {
        "af": 6,
        "avg": 127.567585,
        "dst_addr": "2001:500:9f::42",
        "dst_name": "2001:500:9f::42",
        "dup": 0,
        "from": "2a01:5ec0:2027:4494:c225:e9ff:fea8:7c54",
        "fw": 4780,
        "lts": 80,
        "max": 131.50166,
        "min": 124.858715,
        "msm_id": 2008,
        "msm_name": "Ping",
        "prb_id": 34057,
        "proto": "ICMP",
        "rcvd": 3,
        "result": [
            {
                "rtt": 131.50166
            },
            {
                "rtt": 126.34238
            },
            {
                "rtt": 124.858715
            }
        ],
        "sent": 3,
        "size": 20,
        "src_addr": "2a01:5ec0:2027:4494:c225:e9ff:fea8:7c54",
        "step": 240,
        "stored_timestamp": 1559831815,
        "timestamp": 1559831526,
        "ttl": 45,
        "type": "ping"
    },
    {
        "af": 6,
        "avg": 155.7526666667,
        "dst_addr": "2001:500:9f::42",
        "dst_name": "2001:500:9f::42",
        "dup": 0,
        "from": "2a01:5ec0:2027:4494:c225:e9ff:fea8:7c54",
        "fw": 4780,
        "lts": 67,
        "max": 159.80584,
        "min": 153.22679,
        "msm_id": 2008,
        "msm_name": "Ping",
        "prb_id": 34057,
        "proto": "ICMP",
        "rcvd": 3,
        "result": [
            {
                "rtt": 159.80584
            },
            {
                "rtt": 154.22537
            },
            {
                "rtt": 153.22679
            }
        ],
        "sent": 3,
        "size": 20,
        "src_addr": "2a01:5ec0:2027:4494:c225:e9ff:fea8:7c54",
        "step": 240,
        "stored_timestamp": 1559831870,
        "timestamp": 1559831767,
        "ttl": 45,
        "type": "ping"
    },
    {
        "af": 6,
        "avg": 130.48006,
        "dst_addr": "2001:500:9f::42",
        "dst_name": "2001:500:9f::42",
        "dup": 0,
        "from": "2a01:5ec0:2027:4494:c225:e9ff:fea8:7c54",
        "fw": 4780,
        "lts": 32,
        "max": 132.795785,
        "min": 126.34586,
        "msm_id": 2008,
        "msm_name": "Ping",
        "prb_id": 34057,
        "proto": "ICMP",
        "rcvd": 3,
        "result": [
            {
                "rtt": 132.795785
            },
            {
                "rtt": 132.298535
            },
            {
                "rtt": 126.34586
            }
        ],
        "sent": 3,
        "size": 20,
        "src_addr": "2a01:5ec0:2027:4494:c225:e9ff:fea8:7c54",
        "step": 240,
        "stored_timestamp": 1559832080,
        "timestamp": 1559832007,
        "ttl": 45,
        "type": "ping"
    },
    {
        "af": 6,
        "avg": 133.001005,
        "dst_addr": "2001:500:9f::42",
        "dst_name": "2001:500:9f::42",
        "dup": 0,
        "from": "2a01:5ec0:2027:4494:c225:e9ff:fea8:7c54",
        "fw": 4780,
        "lts": 82,
        "max": 137.09476,
        "min": 130.42322,
        "msm_id": 2008,
        "msm_name": "Ping",
        "prb_id": 34057,
        "proto": "ICMP",
        "rcvd": 3,
        "result": [
            {
                "rtt": 137.09476
            },
            {
                "rtt": 131.485035
            },
            {
                "rtt": 130.42322
            }
        ],
        "sent": 3,
        "size": 20,
        "src_addr": "2a01:5ec0:2027:4494:c225:e9ff:fea8:7c54",
        "step": 240,
        "stored_timestamp": 1559832390,
        "timestamp": 1559832247,
        "ttl": 45,
        "type": "ping"
    },
    {
        "af": 6,
        "avg": 147.2181033333,
        "dst_addr": "2001:500:9f::42",
        "dst_name": "2001:500:9f::42",
        "dup": 0,
        "from": "2a01:5ec0:2027:4494:c225:e9ff:fea8:7c54",
        "fw": 4780,
        "lts": 68,
        "max": 151.03969,
        "min": 144.53037,
        "msm_id": 2008,
        "msm_name": "Ping",
        "prb_id": 34057,
        "proto": "ICMP",
        "rcvd": 3,
        "result": [
            {
                "rtt": 151.03969
            },
            {
                "rtt": 146.08425
            },
            {
                "rtt": 144.53037
            }
        ],
        "sent": 3,
        "size": 20,
        "src_addr": "2a01:5ec0:2027:4494:c225:e9ff:fea8:7c54",
        "step": 240,
        "stored_timestamp": 1559832669,
        "timestamp": 1559832486,
        "ttl": 45,
        "type": "ping"
    }
]