[
    {
        "af": 6,
        "avg": 84.1194366667,
        "dst_addr": "2001:500:2f::f",
        "dst_name": "2001:500:2f::f",
        "dup": 0,
        "from": "2001:16a2:14e0:3300:c225:e9ff:fea8:46c4",
        "fw": 4970,
        "lts": 56,
        "max": 84.539745,
        "min": 83.863345,
        "msm_id": 2004,
        "msm_name": "Ping",
        "prb_id": 34114,
        "proto": "ICMP",
        "rcvd": 3,
        "result": [
            {
                "rtt": 84.539745
            },
            {
                "rtt": 83.863345
            },
            {
                "rtt": 83.95522
            }
        ],
        "sent": 3,
        "size": 20,
        "src_addr": "2001:16a2:14e0:3300:c225:e9ff:fea8:46c4",
        "step": 240,
        "stored_timestamp": 1559283503,
        "timestamp": 1559283384,
        "ttl": 58,
        "type": "ping"
    },
    {
        "af": 6,
        "avg": 84.3548366667,
        "dst_addr": "2001:500:2f::f",
        "dst_name": "2001:500:2f::f",
        "dup": 0,
        "from": "2001:16a2:14e0:3300:c225:e9ff:fea8:46c4",
        "fw": 4970,
        "lts": 21,
        "max": 84.417435,
        "min": 84.261375,
        "msm_id": 2004,
        "msm_name": "Ping",
        "prb_id": 34114,
        "proto": "ICMP",
        "rcvd": 3,
        "result": [
            {
                "rtt": 84.3857
            },
            {
                "rtt": 84.261375
            },
            {
                "rtt": 84.417435
            }
        ],
        "sent": 3,
        "size": 20,
        "src_addr": "2001:16a2:14e0:3300:c225:e9ff:fea8:46c4",
        "step": 240,
        "stored_timestamp": 1559283670,
        "timestamp": 1559283627,
        "ttl": 58,
        "type": "ping"
    },
    {
        "af": 6,
        "avg": 84.2809283333,
        "dst_addr": "2001:500:2f::f",
        "dst_name": "2001:500:2f::f",
        "dup": 0,
        "from": "2001:16a2:14e0:3300:c225:e9ff:fea8:46c4",
        "fw": 4970,
        "lts": 15,
        "max": 84.416395,
        "min": 84.09606,
        "msm_id": 2004,
        "msm_name": "Ping",
        "prb_id": 34114,
        "proto": "ICMP",
        "rcvd": 3,
        "result": [
            {
                "rtt": 84.33033
            },
            {
                "rtt": 84.09606
            },
            {
                "rtt": 84.416395
            }
        ],
        "sent": 3,
        "size": 20,
        "src_addr": "2001:16a2:14e0:3300:c225:e9ff:fea8:46c4",
        "step": 240,
        "stored_timestamp": 1559283985,
        "timestamp": 1559283867,
        "ttl": 58,
        "type": "ping"
    },
    {
        "af": 6,
        "avg": 83.941945,
        "dst_addr": "2001:500:2f::f",
        "dst_name": "2001:500:2f::f",
        "dup": 0,
        "from": "2001:16a2:14e0:3300:c225:e9ff:fea8:46c4",
        "fw": 4970,
        "lts": 54,
        "max": 84.00021,
        "min": 83.90168,
        "msm_id": 2004,
        "msm_name": "Ping",
        "prb_id": 34114,
        "proto": "ICMP",
        "rcvd": 3,
        "result": [
            {
                "rtt": 84.00021
            },
            {
                "rtt": 83.923945
            },
            {
                "rtt": 83.90168
            }
        ],
        "sent": 3,
        "size": 20,
        "src_addr": "2001:16a2:14e0:3300:c225:e9ff:fea8:46c4",
        "step": 240,
        "stored_timestamp": 1559284233,
        "timestamp": 1559284106,
        "ttl": 58,
        "type": "ping"
    },
    {
        "af": 6,
        "avg": 83.9911783333,
        "dst_addr": "2001:500:2f::f",
        "dst_name": "2001:500:2f::f",
        "dup": 0,
        "from": "2001:16a2:14e0:3300:c225:e9ff:fea8:46c4",
        "fw": 4970,
        "lts": 10,
        "max": 84.224685,
        "min": 83.666175,
        "msm_id": 2004,
        "msm_name": "Ping",
        "prb_id": 34114,
        "proto": "ICMP",
        "rcvd": 3,
        "result": [
            {
                "rtt": 84.082675
            },
            {
                "rtt": 83.666175
            },
            {
                "rtt": 84.224685
            }
        ],
        "sent": 3,
        "size": 20,
        "src_addr": "2001:16a2:14e0:3300:c225:e9ff:fea8:46c4",
        "step": 240,
        "stored_timestamp": 1559284485,
        "timestamp": 1559284346,
        "ttl": 58,
        "type": "ping"
    },
    {
        "af": 6,
        "avg": 83.9115333333,
        "dst_addr": "2001:500:2f::f",
        "dst_name": "2001:500:2f::f",
        "dup": 0,
        "from": "2001:16a2:14e0:3300:c225:e9ff:fea8:46c4",
        "fw": 4970,
        "lts": 32,
        "max": 84.273895,
        "min": 83.545165,
        "msm_id": 2004,
        "msm_name": "Ping",
        "prb_id": 34114,
        "proto": "ICMP",
        "rcvd": 3,
        "result": [
            {
                "rtt": 83.91554
            },
            {
                "rtt": 83.545165
            },
            {
                "rtt": 84.273895
            }
        ],
        "sent": 3,
        "size": 20,
        "src_addr": "2001:16a2:14e0:3300:c225:e9ff:fea8:46c4",
        "step": 240,
        "stored_timestamp": 1559284690,
        "timestamp": 1559284587,
        "ttl": 58,
        "type": "ping"
    },
    {
        "af": 6,
        "avg": 84.1582783333,
        "dst_addr": "2001:500:2f::f",
        "dst_name": "2001:500:2f::f",
        "dup": 0,
        "from": "2001:16a2:14e0:3300:c225:e9ff:fea8:46c4",
        "fw": 4970,
        "lts": 53,
        "max": 84.64671,
        "min": 83.805935,
        "msm_id": 2004,
        "msm_name": "Ping",
        "prb_id": 34114,
        "proto": "ICMP",
        "rcvd": 3,
        "result": [
            {
                "rtt": 84.64671
            },
            {
                "rtt": 84.02219
            },
            {
                "rtt": 83.805935
            }
        ],
        "sent": 3,
        "size": 20,
        "src_addr": "2001:16a2:14e0:3300:c225:e9ff:fea8:46c4",
        "step": 240,
        "stored_timestamp": 1559284927,
        "timestamp": 1559284826,
        "ttl": 58,
        "type": "ping"
    },
    {
        "af": 6,
        "avg": 83.9919216667,
        "dst_addr": "2001:500:2f::f",
        "dst_name": "2001:500:2f::f",
        "dup": 0,
        "from": "2001:16a2:14e0:3300:c225:e9ff:fea8:46c4",
        "fw": 4970,
        "lts": 19,
        "max": 84.58927,
        "min": 83.50546,
        "msm_id": 2004,
        "msm_name": "Ping",
        "prb_id": 34114,
        "proto": "ICMP",
        "rcvd": 3,
        "result": [
            {
                "rtt": 84.58927
            },
            {
                "rtt": 83.881035
            },
            {
                "rtt": 83.50546
            }
        ],
        "sent": 3,
        "size": 20,
        "src_addr": "2001:16a2:14e0:3300:c225:e9ff:fea8:46c4",
        "step": 240,
        "stored_timestamp": 1559285217,
        "timestamp": 1559285064,
        "ttl": 58,
        "type": "ping"
    },
    {
        "af": 6,
        "avg": 83.9696216667,
        "dst_addr": "2001:500:2f::f",
        "dst_name": "2001:500:2f::f",
        "dup": 0,
        "from": "2001:16a2:14e0:3300:c225:e9ff:fea8:46c4",
        "fw": 4970,
        "lts": 10,
        "max": 84.33435,
        "min": 83.5115,
        "msm_id": 2004,
        "msm_name": "Ping",
        "prb_id": 34114,
        "proto": "ICMP",
        "rcvd": 3,
        "result": [
            {
                "rtt": 84.33435
            },
            {
                "rtt": 83.5115
            },
            {
                "rtt": 84.063015
            }
        ],
        "sent": 3,
        "size": 20,
        "src_addr": "2001:16a2:14e0:3300:c225:e9ff:fea8:46c4",
        "step": 240,
        "stored_timestamp": 1559285430,
        "timestamp": 1559285304,
        "ttl": 58,
        "type": "ping"
    },
    {
        "af": 6,
        "avg": 84.176155,
        "dst_addr": "2001:500:2f::f",
        "dst_name": "2001:500:2f::f",
        "dup": 0,
        "from": "2001:16a2:14e0:3300:c225:e9ff:fea8:46c4",
        "fw": 4970,
        "lts": 63,
        "max": 84.2674,
        "min": 84.01564,
        "msm_id": 2004,
        "msm_name": "Ping",
        "prb_id": 34114,
        "proto": "ICMP",
        "rcvd": 3,
        "result": [
            {
                "rtt": 84.2674
            },
            {
                "rtt": 84.01564
            },
            {
                "rtt": 84.245425
            }
        ],
        "sent": 3,
        "size": 20,
        "src_addr": "2001:16a2:14e0:3300:c225:e9ff:fea8:46c4",
        "step": 240,
        "stored_timestamp": 1559285663,
        "timestamp": 1559285545,
        "ttl": 58,
        "type": "ping"
    },
    {
        "af": 6,
        "avg": 83.8185566667,
        "dst_addr": "2001:500:2f::f",
        "dst_name": "2001:500:2f::f",
        "dup": 0,
        "from": "2001:16a2:14e0:3300:c225:e9ff:fea8:46c4",
        "fw": 4970,
        "lts": 13,
        "max": 83.909945,
        "min": 83.73467,
        "msm_id": 2004,
        "msm_name": "Ping",
        "prb_id": 34114,
        "proto": "ICMP",
        "rcvd": 3,
        "result": [
            {
                "rtt": 83.811055
            },
            {
                "rtt": 83.909945
            },
            {
                "rtt": 83.73467
            }
        ],
        "sent": 3,
        "size": 20,
        "src_addr": "2001:16a2:14e0:3300:c225:e9ff:fea8:46c4",
        "step": 240,
        "stored_timestamp": 1559285851,
        "timestamp": 1559285785,
        "ttl": 58,
        "type": "ping"
    },
    {
        "af": 6,
        "avg": 84.16231,
        "dst_addr": "2001:500:2f::f",
        "dst_name": "2001:500:2f::f",
        "dup": 0,
        "from": "2001:16a2:14e0:3300:c225:e9ff:fea8:46c4",
        "fw": 4970,
        "lts": 24,
        "max": 84.62839,
        "min": 83.86168,
        "msm_id": 2004,
        "msm_name": "Ping",
        "prb_id": 34114,
        "proto": "ICMP",
        "rcvd": 3,
        "result": [
            {
                "rtt": 83.86168
            },
            {
                "rtt": 84.62839
            },
            {
                "rtt": 83.99686
            }
        ],
        "sent": 3,
        "size": 20,
        "src_addr": "2001:16a2:14e0:3300:c225:e9ff:fea8:46c4",
        "step": 240,
        "stored_timestamp": 1559286482,
        "timestamp": 1559286027,
        "ttl": 58,
        "type": "ping"
    },
    {
        "af": 6,
        "avg": 84.5154633333,
        "dst_addr": "2001:500:2f::f",
        "dst_name": "2001:500:2f::f",
        "dup": 0,
        "from": "2001:16a2:14e0:3300:c225:e9ff:fea8:46c4",
        "fw": 4970,
        "lts": 59,
        "max": 84.92596,
        "min": 83.907415,
        "msm_id": 2004,
        "msm_name": "Ping",
        "prb_id": 34114,
        "proto": "ICMP",
        "rcvd": 3,
        "result": [
            {
                "rtt": 84.713015
            },
            {
                "rtt": 84.92596
            },
            {
                "rtt": 83.907415
            }
        ],
        "sent": 3,
        "size": 20,
        "src_addr": "2001:16a2:14e0:3300:c225:e9ff:fea8:46c4",
        "step": 240,
        "stored_timestamp": 1559286607,
        "timestamp": 1559286266,
        "ttl": 58,
        "type": "ping"
    },
    {
        "af": 6,
        "avg": 84.2455933333,
        "dst_addr": "2001:500:2f::f",
        "dst_name": "2001:500:2f::f",
        "dup": 0,
        "from": "2001:16a2:14e0:3300:c225:e9ff:fea8:46c4",
        "fw": 4970,
        "lts": 22,
        "max": 84.627465,
        "min": 83.938765,
        "msm_id": 2004,
        "msm_name": "Ping",
        "prb_id": 34114,
        "proto": "ICMP",
        "rcvd": 3,
        "result": [
            {
                "rtt": 84.627465
            },
            {
                "rtt": 83.938765
            },
            {
                "rtt": 84.17055
            }
        ],
        "sent": 3,
        "size": 20,
        "src_addr": "2001:16a2:14e0:3300:c225:e9ff:fea8:46c4",
        "step": 240,
        "stored_timestamp": 1559286698,
        "timestamp": 1559286506,
        "ttl": 58,
        "type": "ping"
    },
    {
        "af": 6,
        "avg": 84.0726866667,
        "dst_addr": "2001:500:2f::f",
        "dst_name": "2001:500:2f::f",
        "dup": 0,
        "from": "2001:16a2:14e0:3300:c225:e9ff:fea8:46c4",
        "fw": 4970,
        "lts": 25,
        "max": 84.302165,
        "min": 83.94016,
        "msm_id": 2004,
        "msm_name": "Ping",
        "prb_id": 34114,
        "proto": "ICMP",
        "rcvd": 3,
        "result": [
            {
                "rtt": 83.975735
            },
            {
                "rtt": 83.94016
            },
            {
                "rtt": 84.302165
            }
        ],
        "sent": 3,
        "size": 20,
        "src_addr": "2001:16a2:14e0:3300:c225:e9ff:fea8:46c4",
        "step": 240,
        "stored_timestamp": 1559286864,
        "timestamp": 1559286745,
        "ttl": 58,
        "type": "ping"
    }
]