[
    {
        "af": 6,
        "avg": 284.443961,
        "dst_addr": "2001:500:2f::f",
        "dst_name": "2001:500:2f::f",
        "dup": 0,
        "from": "2a00:1ce0:0:4::cc1",
        "fw": 4790,
        "lts": 117,
        "max": 292.513594,
        "min": 278.989112,
        "msm_id": 2004,
        "msm_name": "Ping",
        "prb_id": 2610,
        "proto": "ICMP",
        "rcvd": 3,
        "result": [
            {
                "rtt": 281.829177
            },
            {
                "rtt": 278.989112
            },
            {
                "rtt": 292.513594
            }
        ],
        "sent": 3,
        "size": 20,
        "src_addr": "2a00:1ce0:0:4::cc1",
        "step": 240,
        "stored_timestamp": 1557302485,
        "timestamp": 1557302438,
        "ttl": 52,
        "type": "ping"
    },
    {
        "af": 6,
        "avg": 279.1119923333,
        "dst_addr": "2001:500:2f::f",
        "dst_name": "2001:500:2f::f",
        "dup": 0,
        "from": "2a00:1ce0:0:4::cc1",
        "fw": 4790,
        "lts": 354,
        "max": 279.873848,
        "min": 278.218041,
        "msm_id": 2004,
        "msm_name": "Ping",
        "prb_id": 2610,
        "proto": "ICMP",
        "rcvd": 3,
        "result": [
            {
                "rtt": 279.244088
            },
            {
                "rtt": 279.873848
            },
            {
                "rtt": 278.218041
            }
        ],
        "sent": 3,
        "size": 20,
        "src_addr": "2a00:1ce0:0:4::cc1",
        "step": 240,
        "stored_timestamp": 1557302811,
        "timestamp": 1557302675,
        "ttl": 52,
        "type": "ping"
    },
    {
        "af": 6,
        "avg": 286.4190013333,
        "dst_addr": "2001:500:2f::f",
        "dst_name": "2001:500:2f::f",
        "dup": 0,
        "from": "2a00:1ce0:0:4::cc1",
        "fw": 4790,
        "lts": 596,
        "max": 290.083642,
        "min": 280.439096,
        "msm_id": 2004,
        "msm_name": "Ping",
        "prb_id": 2610,
        "proto": "ICMP",
        "rcvd": 3,
        "result": [
            {
                "rtt": 280.439096
            },
            {
                "rtt": 288.734266
            },
            {
                "rtt": 290.083642
            }
        ],
        "sent": 3,
        "size": 20,
        "src_addr": "2a00:1ce0:0:4::cc1",
        "step": 240,
        "stored_timestamp": 1557302984,
        "timestamp": 1557302917,
        "ttl": 52,
        "type": "ping"
    },
    {
        "af": 6,
        "avg": 475.3055673333,
        "dst_addr": "2001:500:2f::f",
        "dst_name": "2001:500:2f::f",
        "dup": 0,
        "from": "2a00:1ce0:0:4::cc1",
        "fw": 4790,
        "lts": 834,
        "max": 856.039852,
        "min": 284.682297,
        "msm_id": 2004,
        "msm_name": "Ping",
        "prb_id": 2610,
        "proto": "ICMP",
        "rcvd": 3,
        "result": [
            {
                "rtt": 856.039852
            },
            {
                "rtt": 285.194553
            },
            {
                "rtt": 284.682297
            }
        ],
        "sent": 3,
        "size": 20,
        "src_addr": "2a00:1ce0:0:4::cc1",
        "step": 240,
        "stored_timestamp": 1557303236,
        "timestamp": 1557303155,
        "ttl": 52,
        "type": "ping"
    },
    {
        "af": 6,
        "avg": 286.4474173333,
        "dst_addr": "2001:500:2f::f",
        "dst_name": "2001:500:2f::f",
        "dup": 0,
        "from": "2a00:1ce0:0:4::cc1",
        "fw": 4790,
        "lts": 1,
        "max": 291.053626,
        "min": 283.925049,
        "msm_id": 2004,
        "msm_name": "Ping",
        "prb_id": 2610,
        "proto": "ICMP",
        "rcvd": 3,
        "result": [
            {
                "rtt": 283.925049
            },
            {
                "rtt": 284.363577
            },
            {
                "rtt": 291.053626
            }
        ],
        "sent": 3,
        "size": 20,
        "src_addr": "2a00:1ce0:0:4::cc1",
        "step": 240,
        "stored_timestamp": 1557303523,
        "timestamp": 1557303396,
        "ttl": 52,
        "type": "ping"
    },
    {
        "af": 6,
        "avg": 283.2161853333,
        "dst_addr": "2001:500:2f::f",
        "dst_name": "2001:500:2f::f",
        "dup": 0,
        "from": "2a00:1ce0:0:4::cc1",
        "fw": 4790,
        "lts": 243,
        "max": 287.490874,
        "min": 281.076537,
        "msm_id": 2004,
        "msm_name": "Ping",
        "prb_id": 2610,
        "proto": "ICMP",
        "rcvd": 3,
        "result": [
            {
                "rtt": 287.490874
            },
            {
                "rtt": 281.076537
            },
            {
                "rtt": 281.081145
            }
        ],
        "sent": 3,
        "size": 20,
        "src_addr": "2a00:1ce0:0:4::cc1",
        "step": 240,
        "stored_timestamp": 1557303712,
        "timestamp": 1557303638,
        "ttl": 52,
        "type": "ping"
    },
    {
        "af": 6,
        "avg": 280.530488,
        "dst_addr": "2001:500:2f::f",
        "dst_name": "2001:500:2f::f",
        "dup": 0,
        "from": "2a00:1ce0:0:4::cc1",
        "fw": 4790,
        "lts": 115,
        "max": 280.932152,
        "min": 279.909176,
        "msm_id": 2004,
        "msm_name": "Ping",
        "prb_id": 2610,
        "proto": "ICMP",
        "rcvd": 3,
        "result": [
            {
                "rtt": 280.750136
            },
            {
                "rtt": 280.932152
            },
            {
                "rtt": 279.909176
            }
        ],
        "sent": 3,
        "size": 20,
        "src_addr": "2a00:1ce0:0:4::cc1",
        "step": 240,
        "stored_timestamp": 1557303943,
        "timestamp": 1557303877,
        "ttl": 52,
        "type": "ping"
    },
    {
        "af": 6,
        "avg": 281.9507766667,
        "dst_addr": "2001:500:2f::f",
        "dst_name": "2001:500:2f::f",
        "dup": 0,
        "from": "2a00:1ce0:0:4::cc1",
        "fw": 4790,
        "lts": 231,
        "max": 284.96953,
        "min": 280.036664,
        "msm_id": 2004,
        "msm_name": "Ping",
        "prb_id": 2610,
        "proto": "ICMP",
        "rcvd": 3,
        "result": [
            {
                "rtt": 284.96953
            },
            {
                "rtt": 280.846136
            },
            {
                "rtt": 280.036664
            }
        ],
        "sent": 3,
        "size": 20,
        "src_addr": "2a00:1ce0:0:4::cc1",
        "step": 240,
        "stored_timestamp": 1557304248,
        "timestamp": 1557304115,
        "ttl": 52,
        "type": "ping"
    },
    {
        "af": 6,
        "avg": 279.6286003333,
        "dst_addr": "2001:500:2f::f",
        "dst_name": "2001:500:2f::f",
        "dup": 0,
        "from": "2a00:1ce0:0:4::cc1",
        "fw": 4790,
        "lts": 238,
        "max": 280.37228,
        "min": 278.480697,
        "msm_id": 2004,
        "msm_name": "Ping",
        "prb_id": 2610,
        "proto": "ICMP",
        "rcvd": 3,
        "result": [
            {
                "rtt": 280.37228
            },
            {
                "rtt": 280.032824
            },
            {
                "rtt": 278.480697
            }
        ],
        "sent": 3,
        "size": 20,
        "src_addr": "2a00:1ce0:0:4::cc1",
        "step": 240,
        "stored_timestamp": 1557304421,
        "timestamp": 1557304358,
        "ttl": 52,
        "type": "ping"
    },
    {
        "af": 6,
        "avg": 282.6716726667,
        "dst_addr": "2001:500:2f::f",
        "dst_name": "2001:500:2f::f",
        "dup": 0,
        "from": "2a00:1ce0:0:4::cc1",
        "fw": 4790,
        "lts": 120,
        "max": 288.701242,
        "min": 279.346232,
        "msm_id": 2004,
        "msm_name": "Ping",
        "prb_id": 2610,
        "proto": "ICMP",
        "rcvd": 3,
        "result": [
            {
                "rtt": 288.701242
            },
            {
                "rtt": 279.967544
            },
            {
                "rtt": 279.346232
            }
        ],
        "sent": 3,
        "size": 20,
        "src_addr": "2a00:1ce0:0:4::cc1",
        "step": 240,
        "stored_timestamp": 1557304680,
        "timestamp": 1557304596,
        "ttl": 52,
        "type": "ping"
    },
    {
        "af": 6,
        "avg": 280.9651763333,
        "dst_addr": "2001:500:2f::f",
        "dst_name": "2001:500:2f::f",
        "dup": 0,
        "from": "2a00:1ce0:0:4::cc1",
        "fw": 4790,
        "lts": 182,
        "max": 283.336761,
        "min": 279.51596,
        "msm_id": 2004,
        "msm_name": "Ping",
        "prb_id": 2610,
        "proto": "ICMP",
        "rcvd": 3,
        "result": [
            {
                "rtt": 279.51596
            },
            {
                "rtt": 280.042808
            },
            {
                "rtt": 283.336761
            }
        ],
        "sent": 3,
        "size": 20,
        "src_addr": "2a00:1ce0:0:4::cc1",
        "step": 240,
        "stored_timestamp": 1557304981,
        "timestamp": 1557304837,
        "ttl": 52,
        "type": "ping"
    },
    {
        "af": 6,
        "avg": 280.0586806667,
        "dst_addr": "2001:500:2f::f",
        "dst_name": "2001:500:2f::f",
        "dup": 0,
        "from": "2a00:1ce0:0:4::cc1",
        "fw": 4790,
        "lts": 60,
        "max": 282.189368,
        "min": 278.801721,
        "msm_id": 2004,
        "msm_name": "Ping",
        "prb_id": 2610,
        "proto": "ICMP",
        "rcvd": 3,
        "result": [
            {
                "rtt": 282.189368
            },
            {
                "rtt": 278.801721
            },
            {
                "rtt": 279.184953
            }
        ],
        "sent": 3,
        "size": 20,
        "src_addr": "2a00:1ce0:0:4::cc1",
        "step": 240,
        "stored_timestamp": 1557305159,
        "timestamp": 1557305074,
        "ttl": 52,
        "type": "ping"
    },
    {
        "af": 6,
        "avg": 284.0576566667,
        "dst_addr": "2001:500:2f::f",
        "dst_name": "2001:500:2f::f",
        "dup": 0,
        "from": "2a00:1ce0:0:4::cc1",
        "fw": 4790,
        "lts": 304,
        "max": 285.583161,
        "min": 282.133304,
        "msm_id": 2004,
        "msm_name": "Ping",
        "prb_id": 2610,
        "proto": "ICMP",
        "rcvd": 3,
        "result": [
            {
                "rtt": 285.583161
            },
            {
                "rtt": 282.133304
            },
            {
                "rtt": 284.456505
            }
        ],
        "sent": 3,
        "size": 20,
        "src_addr": "2a00:1ce0:0:4::cc1",
        "step": 240,
        "stored_timestamp": 1557305386,
        "timestamp": 1557305318,
        "ttl": 52,
        "type": "ping"
    },
    {
        "af": 6,
        "avg": 284.6927933333,
        "dst_addr": "2001:500:2f::f",
        "dst_name": "2001:500:2f::f",
        "dup": 0,
        "from": "2a00:1ce0:0:4::cc1",
        "fw": 4790,
        "lts": 7,
        "max": 289.009978,
        "min": 281.419065,
        "msm_id": 2004,
        "msm_name": "Ping",
        "prb_id": 2610,
        "proto": "ICMP",
        "rcvd": 3,
        "result": [
            {
                "rtt": 281.419065
            },
            {
                "rtt": 289.009978
            },
            {
                "rtt": 283.649337
            }
        ],
        "sent": 3,
        "size": 20,
        "src_addr": "2a00:1ce0:0:4::cc1",
        "step": 240,
        "stored_timestamp": 1557305691,
        "timestamp": 1557305557,
        "ttl": 52,
        "type": "ping"
    },
    {
        "af": 6,
        "avg": 480.8717766667,
        "dst_addr": "2001:500:2f::f",
        "dst_name": "2001:500:2f::f",
        "dup": 0,
        "from": "2a00:1ce0:0:4::cc1",
        "fw": 4790,
        "lts": 126,
        "max": 878.643633,
        "min": 280.636472,
        "msm_id": 2004,
        "msm_name": "Ping",
        "prb_id": 2610,
        "proto": "ICMP",
        "rcvd": 3,
        "result": [
            {
                "rtt": 280.636472
            },
            {
                "rtt": 878.643633
            },
            {
                "rtt": 283.335225
            }
        ],
        "sent": 3,
        "size": 20,
        "src_addr": "2a00:1ce0:0:4::cc1",
        "step": 240,
        "stored_timestamp": 1557305883,
        "timestamp": 1557305798,
        "ttl": 52,
        "type": "ping"
    }
]